psusannx_email/__init__.py
psusannx_email/sendgrid_email.py
psusannx_email-0.1.4.dist-info/LICENSE
psusannx_email-0.1.4.dist-info/METADATA
psusannx_email-0.1.4.dist-info/WHEEL
psusannx_email-0.1.4.dist-info/top_level.txt
psusannx_email-0.1.4.dist-info/RECORD
