Metadata-Version: 2.1
Name: psusannx-email
Version: 0.1.4
Summary: A package with a function for sending emails easily using sendgrid.
Author: Jamie O'Brien
Project-URL: Source Code, https://github.com/jamieob63/psusannx_email.git
Project-URL: Bug Tracker, https://github.com/jamieob63/psusannx_email.git/issues
License-File: LICENSE
Requires-Dist: sendgrid (>=6.9.7)
